edudigitaldocs/__init__.py
edudigitaldocs-0.1.dist-info/LICENSE.txt
edudigitaldocs-0.1.dist-info/METADATA
edudigitaldocs-0.1.dist-info/WHEEL
edudigitaldocs-0.1.dist-info/top_level.txt
edudigitaldocs-0.1.dist-info/RECORD
